[{"jp": "そうですか", "reading_kana": "そうですか", "en": "I see", "ts": 1757195539.730722}, {"jp": "なるほど", "reading_kana": "なるほど", "en": "I see", "ts": 1757195539.730722}, {"jp": "どういう感じ", "reading_kana": "どういうかんじ", "en": "What kind of feeling", "ts": 1757195539.730722}, {"jp": "似てるね", "reading_kana": "にてるね", "en": "It's similar", "ts": 1757195539.730722}, {"jp": "何ですか", "reading_kana": "なんですか", "en": "What is it?", "ts": 1757195540.906212}, {"jp": "見せて", "reading_kana": "みせて", "en": "Show me", "ts": 1757195540.906212}, {"jp": "どれ", "reading_kana": "どれ", "en": "Which one?", "ts": 1757195540.906212}, {"jp": "どこへ", "reading_kana": "どこへ", "en": "where to", "ts": 1757195542.290915}, {"jp": "どうやって", "reading_kana": "どうやって", "en": "how", "ts": 1757195542.290915}, {"jp": "本当に", "reading_kana": "ほんとうに", "en": "really", "ts": 1757195542.290915}, {"jp": "確認しよう", "reading_kana": "かくにんしよう", "en": "let's check", "ts": 1757195542.290915}, {"jp": "どこに移動しますか", "reading_kana": "どこにいどうしますか", "en": "Where should I move?", "ts": 1757195544.189182}, {"jp": "手伝いましょうか", "reading_kana": "てつだいましょうか", "en": "Shall I help?", "ts": 1757195544.189182}, {"jp": "準備はいいですか", "reading_kana": "じゅんびはいいですか", "en": "Are you ready?", "ts": 1757195544.189182}, {"jp": "何を待っているの？", "reading_kana": "なにをまっているの？", "en": "What are you waiting for?", "ts": 1757195548.370281}, {"jp": "どこにいるの？", "reading_kana": "どこにいるの？", "en": "Where are you?", "ts": 1757195548.370281}, {"jp": "静かにして", "reading_kana": "しずかにして", "en": "Be quiet", "ts": 1757195548.370281}, {"jp": "落ち着いて", "reading_kana": "おちついて", "en": "Calm down", "ts": 1757195548.370281}, {"jp": "次はどうする？", "reading_kana": "つぎはどうする？", "en": "What to do next?", "ts": 1757195548.4771268}, {"jp": "練習を続ける", "reading_kana": "れんしゅうをつづける", "en": "Continue practicing", "ts": 1757195548.4771268}, {"jp": "他の動きも試す", "reading_kana": "ほかのうごきもためす", "en": "Try other moves", "ts": 1757195548.4771268}, {"jp": "大丈夫？", "reading_kana": "だいじょうぶ？", "en": "Are you okay?", "ts": 1757195550.040598}, {"jp": "どうしたの？", "reading_kana": "どうしたの？", "en": "What's wrong?", "ts": 1757195550.040598}, {"jp": "気をつけてね", "reading_kana": "きをつけてね", "en": "Be careful.", "ts": 1757195550.040598}, {"jp": "どうしたの？", "reading_kana": "どうしたの？", "en": "What's wrong?", "ts": 1757195553.4448059}, {"jp": "次は何をする？", "reading_kana": "つぎはなにをする？", "en": "What next?", "ts": 1757195553.4448059}, {"jp": "気にしないで", "reading_kana": "きにしないで", "en": "Don't worry", "ts": 1757195553.4448059}, {"jp": "元気ですか", "reading_kana": "げんきですか", "en": "Are you well?", "ts": 1757195554.052842}, {"jp": "調子はどう", "reading_kana": "ちょうしはどう", "en": "How's your condition?", "ts": 1757195554.052842}, {"jp": "何かあった", "reading_kana": "なにかあった", "en": "Is something wrong?", "ts": 1757195554.052842}, {"jp": "どうやってジャンプする？", "reading_kana": "どうやってジャンプする？", "en": "How do I jump?", "ts": 1757195559.539233}, {"jp": "もっと高く跳びたい。", "reading_kana": "もっとたかくとびたい。", "en": "I want to jump higher.", "ts": 1757195559.539233}, {"jp": "ジャンプの練習をしよう。", "reading_kana": "ジャンプのれんしゅうをしよう。", "en": "Let's practice jumping.", "ts": 1757195559.539233}, {"jp": "次は何をしよう", "reading_kana": "つぎはなにをしよう", "en": "What shall we do next?", "ts": 1757195564.657485}, {"jp": "それについて話そう", "reading_kana": "それについてはなそう", "en": "Let's talk about that.", "ts": 1757195564.657485}, {"jp": "他に何かある？", "reading_kana": "ほかになにかある？", "en": "Is there anything else?", "ts": 1757195564.657485}, {"jp": "どうすればいい？", "reading_kana": "どうすればいい？", "en": "What should I do?", "ts": 1757195569.419208}, {"jp": "他に方法は？", "reading_kana": "ほかにほうほうは？", "en": "Any other way?", "ts": 1757195569.419208}, {"jp": "安全ですか？", "reading_kana": "あんぜんですか？", "en": "Is it safe?", "ts": 1757195569.419208}, {"jp": "どこへ行く？", "reading_kana": "どこへいく？", "en": "Where are you going?", "ts": 1757195572.3504589}, {"jp": "電車は遅れている。", "reading_kana": "でんしゃはおくれている。", "en": "The train is delayed.", "ts": 1757195572.3504589}, {"jp": "次の駅はどこ？", "reading_kana": "つぎのえきはどこ？", "en": "What's the next station?", "ts": 1757195572.3504589}, {"jp": "気をつけて", "reading_kana": "きをつけて", "en": "Be careful", "ts": 1757195576.5363672}, {"jp": "続けてください", "reading_kana": "つづけてください", "en": "Please continue", "ts": 1757195576.5363672}, {"jp": "何かありますか", "reading_kana": "なにかありますか", "en": "Is there anything?", "ts": 1757195576.5363672}, {"jp": "次は何をしますか", "reading_kana": "つぎは なにを しますか", "en": "What will you do next?", "ts": 1757195581.451794}, {"jp": "もっと詳しく教えて", "reading_kana": "もっと くわしく おしえて", "en": "Tell me more details.", "ts": 1757195581.451794}, {"jp": "他に何かありますか", "reading_kana": "ほかに なにか ありますか", "en": "Is there anything else?", "ts": 1757195581.451794}, {"jp": "次に進む", "reading_kana": "tsugi ni susumu", "en": "Proceed to next", "ts": 1757195585.643944}, {"jp": "確認します", "reading_kana": "kakunin shimasu", "en": "I'll check", "ts": 1757195585.643944}, {"jp": "もう一度", "reading_kana": "mou ichido", "en": "Once more", "ts": 1757195585.643944}, {"jp": "怖いものは何？", "reading_kana": "こわいものはなに？", "en": "What is scary?", "ts": 1757195589.872587}, {"jp": "他に気になることは？", "reading_kana": "ほかにきになることは？", "en": "Anything else you're curious about?", "ts": 1757195589.872587}, {"jp": "もっと詳しく教えて", "reading_kana": "もっとくわしくおしえて", "en": "Tell me more details", "ts": 1757195589.872587}, {"jp": "次は何をしよう", "reading_kana": "つぎはなにをしよう", "en": "What should I do next?", "ts": 1757195592.3313978}, {"jp": "良かったね", "reading_kana": "よかったね", "en": "That's great", "ts": 1757195592.3313978}, {"jp": "宝石を見せて", "reading_kana": "ほうせきをみせて", "en": "Show me the gemstone", "ts": 1757195592.3313978}, {"jp": "何か新しいこと", "reading_kana": "なにかあたらしいこと", "en": "something new", "ts": 1757195596.5519638}, {"jp": "次の挑戦", "reading_kana": "つぎのちょうせん", "en": "next challenge", "ts": 1757195596.5519638}, {"jp": "結果について", "reading_kana": "けっかについて", "en": "about the result", "ts": 1757195596.5519638}, {"jp": "何が動いているの？", "reading_kana": "なにがうごいているの？", "en": "What's moving?", "ts": 1757195600.51676}, {"jp": "どこに行くの？", "reading_kana": "どこにいくの？", "en": "Where are you going?", "ts": 1757195600.51676}, {"jp": "見てみたい。", "reading_kana": "みてみたい。", "en": "I want to see.", "ts": 1757195600.51676}, {"jp": "次はどう動く？", "reading_kana": "つぎはどううごく？", "en": "What next?", "ts": 1757195605.8231301}, {"jp": "進行方向は？", "reading_kana": "しんこうほうこうは？", "en": "Direction?", "ts": 1757195605.8231301}, {"jp": "注意してください。", "reading_kana": "ちゅういしてください。", "en": "Be careful.", "ts": 1757195605.8231301}, {"jp": "何を切るの？", "reading_kana": "なにをきるの？", "en": "What are you cutting?", "ts": 1757195608.383719}, {"jp": "どうしたの？", "reading_kana": "どうしたの？", "en": "What's wrong?", "ts": 1757195608.383719}, {"jp": "気をつけてね", "reading_kana": "きをつけてね", "en": "Be careful.", "ts": 1757195608.383719}, {"jp": "何が起きているの？", "reading_kana": "なにがおきているの？", "en": "What's happening?", "ts": 1757195609.5617101}, {"jp": "誰かいる？", "reading_kana": "だれかいる？", "en": "Is someone there?", "ts": 1757195609.5617101}, {"jp": "助けて！", "reading_kana": "たすけて！", "en": "Help!", "ts": 1757195609.5617101}, {"jp": "もっと詳しく", "reading_kana": "もっとくわしく", "en": "More details", "ts": 1757195613.295438}, {"jp": "次の話題", "reading_kana": "つぎのわだい", "en": "Next topic", "ts": 1757195613.295438}, {"jp": "質問ありますか", "reading_kana": "しつもんありますか", "en": "Any questions?", "ts": 1757195613.295438}, {"jp": "次は何をしよう", "reading_kana": "つぎはなにをしよう", "en": "What shall we do next?", "ts": 1757195618.134542}, {"jp": "場所はここで合ってる？", "reading_kana": "ばしょはここであってる", "en": "Is this the right place?", "ts": 1757195618.134542}, {"jp": "疲れたね", "reading_kana": "つかれたね", "en": "I'm tired.", "ts": 1757195618.134542}, {"jp": "どうしたの？", "reading_kana": "どうしたの？", "en": "What's wrong?", "ts": 1757195621.5586429}, {"jp": "面白いね", "reading_kana": "おもしろいね", "en": "That's funny", "ts": 1757195621.5586429}, {"jp": "驚いた！", "reading_kana": "おどろいた！", "en": "I'm surprised!", "ts": 1757195621.5586429}, {"jp": "何を見ているの？", "reading_kana": "なにをみているの？", "en": "What are you looking at?", "ts": 1757195628.916401}, {"jp": "びっくりした？", "reading_kana": "びっくりした？", "en": "Did I surprise you?", "ts": 1757195628.916401}, {"jp": "何かあったの？", "reading_kana": "なにかあったの？", "en": "Is something wrong?", "ts": 1757195628.916401}, {"jp": "詳しく教えて", "reading_kana": "くわしくおしえて", "en": "Explain in detail", "ts": 1757195632.548003}, {"jp": "何のこと?", "reading_kana": "なんのこと", "en": "What is it about?", "ts": 1757195632.548003}, {"jp": "理解したい", "reading_kana": "りかいしたい", "en": "I want to understand", "ts": 1757195632.548003}, {"jp": "どうしたの？", "reading_kana": "どうしたの？", "en": "What's wrong?", "ts": 1757195636.863505}, {"jp": "驚いたね", "reading_kana": "おどろいたね", "en": "That was surprising.", "ts": 1757195636.863505}, {"jp": "大丈夫？", "reading_kana": "だいじょうぶ？", "en": "Are you okay?", "ts": 1757195636.863505}, {"jp": "何かあったの？", "reading_kana": "なにかあったの？", "en": "Did something happen?", "ts": 1757195640.2276218}, {"jp": "落ち着いて", "reading_kana": "おちついて", "en": "Calm down.", "ts": 1757195640.2276218}, {"jp": "どうしたの？", "reading_kana": "どうしたの？", "en": "What's wrong?", "ts": 1757195640.2276218}, {"jp": "次は何をする？", "reading_kana": "つぎはなにをする？", "en": "What will you do next?", "ts": 1757195645.931371}, {"jp": "面白いね", "reading_kana": "おもしろいね", "en": "That's interesting.", "ts": 1757195645.931371}, {"jp": "ロボットについて話そう", "reading_kana": "ロボットについてはなそう", "en": "Let's talk about robots.", "ts": 1757195645.931371}, {"jp": "どうしたの？", "reading_kana": "どうしたの？", "en": "What's wrong?", "ts": 1757195648.9269109}, {"jp": "面白いね", "reading_kana": "おもしろいね", "en": "That's funny", "ts": 1757195648.9269109}, {"jp": "続けて", "reading_kana": "つづけて", "en": "Keep going", "ts": 1757195648.9269109}, {"jp": "何をもらったの？", "reading_kana": "なにをもらったの？", "en": "What did you get?", "ts": 1757195654.333555}, {"jp": "いいね！", "reading_kana": "いいね！", "en": "Nice!", "ts": 1757195654.333555}, {"jp": "おめでとう！", "reading_kana": "おめでとう！", "en": "Congratulations!", "ts": 1757195654.333555}, {"jp": "行ってみたい", "reading_kana": "いってみたい", "en": "Want to try going", "ts": 1757195657.9649038}, {"jp": "挑戦しよう", "reading_kana": "ちょうせんしよう", "en": "Let's challenge", "ts": 1757195657.9649038}, {"jp": "難しそう", "reading_kana": "むずかしそう", "en": "Looks difficult", "ts": 1757195657.9649038}, {"jp": "また見てください", "reading_kana": "またみてください", "en": "Please watch again", "ts": 1757195662.447577}, {"jp": "次回もお楽しみに", "reading_kana": "じかいもおたのしみに", "en": "Look forward to next time", "ts": 1757195662.447577}, {"jp": "ご視聴ありがとうございます", "reading_kana": "ごしちょうありがとうございます", "en": "Thank you for watching", "ts": 1757195662.447577}, {"jp": "動きますか", "reading_kana": "うごきますか", "en": "Does it move?", "ts": 1757195666.236269}, {"jp": "何のためですか", "reading_kana": "なんのためですか", "en": "What is it for?", "ts": 1757195666.236269}, {"jp": "他にありますか", "reading_kana": "ほかにありますか", "en": "Are there others?", "ts": 1757195666.236269}, {"jp": "どうしたの？", "reading_kana": "どうしたの？", "en": "What's wrong?", "ts": 1757195670.945987}, {"jp": "面白いね", "reading_kana": "おもしろいね", "en": "That's interesting.", "ts": 1757195670.945987}, {"jp": "続けて", "reading_kana": "つづけて", "en": "Keep going.", "ts": 1757195670.945987}, {"jp": "どうなる？", "reading_kana": "どうなる？", "en": "What happens?", "ts": 1757195674.8398552}, {"jp": "次は何？", "reading_kana": "つぎはなに？", "en": "What's next?", "ts": 1757195674.8398552}, {"jp": "気をつけて", "reading_kana": "きをつけて", "en": "Be careful", "ts": 1757195674.8398552}, {"jp": "どうやって", "reading_kana": "どうやって", "en": "How", "ts": 1757195679.128758}, {"jp": "何を", "reading_kana": "なにを", "en": "what", "ts": 1757195679.128758}, {"jp": "次は", "reading_kana": "つぎは", "en": "Next", "ts": 1757195679.128758}, {"jp": "どういう意味？", "reading_kana": "どういういみ？", "en": "What does that mean?", "ts": 1757195684.7709608}, {"jp": "詳しく教えて", "reading_kana": "くわしくおしえて", "en": "Tell me more details", "ts": 1757195684.7709608}, {"jp": "理解できない", "reading_kana": "りかいできない", "en": "I can't understand", "ts": 1757195684.7709608}, {"jp": "どうしたの？", "reading_kana": "どうしたの？", "en": "What's wrong?", "ts": 1757195690.702642}, {"jp": "びっくりした？", "reading_kana": "びっくりした？", "en": "Did you get surprised?", "ts": 1757195690.702642}, {"jp": "大丈夫？", "reading_kana": "だいじょうぶ？", "en": "Are you okay?", "ts": 1757195690.702642}, {"jp": "何をしたらいい？", "reading_kana": "なにをしたらいい？", "en": "What should I do?", "ts": 1757195692.723179}, {"jp": "予定はありますか？", "reading_kana": "よていはありますか？", "en": "Do you have plans?", "ts": 1757195692.723179}, {"jp": "やるべきことリスト", "reading_kana": "やるべきことリスト", "en": "To-do list", "ts": 1757195692.723179}, {"jp": "早くしないと", "reading_kana": "はやくしないと", "en": "If I don't hurry", "ts": 1757195698.395915}, {"jp": "他に方法は", "reading_kana": "ほかにほうほうは", "en": "Are there other ways", "ts": 1757195698.395915}, {"jp": "どうすればいい", "reading_kana": "どうすればいい", "en": "What should I do", "ts": 1757195698.395915}, {"jp": "どこにありますか", "reading_kana": "どこにありますか", "en": "Where is it?", "ts": 1757195702.757687}, {"jp": "他の番号は?", "reading_kana": "ほかのばんごうは?", "en": "Are there other numbers?", "ts": 1757195702.757687}, {"jp": "それは何ですか", "reading_kana": "それはなんですか", "en": "What is that?", "ts": 1757195702.757687}, {"jp": "左側は？", "reading_kana": "ひだりがわは？", "en": "What about the left side?", "ts": 1757195706.445365}, {"jp": "他の番号は？", "reading_kana": "ほかのばんごうは？", "en": "What about other numbers?", "ts": 1757195706.445365}, {"jp": "どこにありますか？", "reading_kana": "どこにありますか？", "en": "Where is it located?", "ts": 1757195706.445365}, {"jp": "次は何？", "reading_kana": "つぎはなに？", "en": "What's next?", "ts": 1757195706.9068449}, {"jp": "それについて話そう", "reading_kana": "それについてはなそう", "en": "Let's talk about that", "ts": 1757195706.9068449}, {"jp": "もう一度言って", "reading_kana": "もういちどいって", "en": "Say it again", "ts": 1757195706.9068449}, {"jp": "記号について", "reading_kana": "きごうについて", "en": "About symbols", "ts": 1757195712.5212018}, {"jp": "図形の意味", "reading_kana": "ずけいのいみ", "en": "Shape meanings", "ts": 1757195712.5212018}, {"jp": "マークの種類", "reading_kana": "まーくのしゅるい", "en": "Types of marks", "ts": 1757195712.5212018}, {"jp": "図形の説明", "reading_kana": "ずけいのせつめい", "en": "Explain the shapes", "ts": 1757195716.409608}, {"jp": "他の記号", "reading_kana": "ほかのきごう", "en": "Other symbols", "ts": 1757195716.409608}, {"jp": "詳細を教えて", "reading_kana": "しょうさいをおしえて", "en": "Tell me more", "ts": 1757195716.409608}, {"jp": "どちらへ行きますか", "reading_kana": "どちらへいきますか", "en": "Where are you going?", "ts": 1757195719.7888398}, {"jp": "左側もありますか", "reading_kana": "ひだりがわもありますか", "en": "Is there also a left side?", "ts": 1757195719.7888398}, {"jp": "道を教えてください", "reading_kana": "みちをおしえてください", "en": "Please show me the way.", "ts": 1757195719.7888398}, {"jp": "次は何をしよう", "reading_kana": "つぎはなにをしよう", "en": "What should I do next?", "ts": 1757195724.336351}, {"jp": "もっと高く跳びたい", "reading_kana": "もっとたかくとびたい", "en": "I want to jump higher.", "ts": 1757195724.336351}, {"jp": "難しいな", "reading_kana": "むずかしいな", "en": "That's difficult.", "ts": 1757195724.336351}, {"jp": "どうしたらいい？", "reading_kana": "どうしたらいい？", "en": "What should I do?", "ts": 1757195729.313513}, {"jp": "他の方法は？", "reading_kana": "ほかのほうほうは？", "en": "Other methods?", "ts": 1757195729.313513}, {"jp": "修理できる？", "reading_kana": "しゅうりできる？", "en": "Can it be repaired?", "ts": 1757195729.313513}, {"jp": "どういう場面で使う？", "reading_kana": "どういうばめんでつかう？", "en": "In what situation is this used?", "ts": 1757195732.78688}, {"jp": "他の表現は？", "reading_kana": "ほかのひょうげんは？", "en": "Are there other expressions?", "ts": 1757195732.78688}, {"jp": "もっと詳しく教えて", "reading_kana": "もっとくわしくおしえて", "en": "Tell me more details.", "ts": 1757195732.78688}, {"jp": "どうやって使う？", "reading_kana": "どうやってつかう？", "en": "How do I use it?", "ts": 1757195736.464755}, {"jp": "他の方法は？", "reading_kana": "ほかのほうほうは？", "en": "Any other options?", "ts": 1757195736.464755}, {"jp": "安全に飛ばせる？", "reading_kana": "あんぜんにとばせる？", "en": "Can it fly safely?", "ts": 1757195736.464755}, {"jp": "何を押すの？", "reading_kana": "なにをおすの？", "en": "What should I push?", "ts": 1757195742.610538}, {"jp": "手伝おうか？", "reading_kana": "てつだおうか？", "en": "Shall I help?", "ts": 1757195742.610538}, {"jp": "もう一度言って", "reading_kana": "もういちどいって", "en": "Say it again.", "ts": 1757195742.610538}, {"jp": "どこ行くの？", "reading_kana": "どこいくの？", "en": "Where are you going?", "ts": 1757195746.003881}, {"jp": "今の場所は？", "reading_kana": "いまのばしょは？", "en": "Where is that now?", "ts": 1757195746.003881}, {"jp": "何してるの？", "reading_kana": "なにしてるの？", "en": "What are you doing?", "ts": 1757195746.003881}, {"jp": "何か話す？", "reading_kana": "なにかはなす？", "en": "Talk about something?", "ts": 1757195749.388263}, {"jp": "どうしたの？", "reading_kana": "どうしたの？", "en": "What's wrong?", "ts": 1757195749.388263}, {"jp": "いい天気だね", "reading_kana": "いいてんきだね", "en": "Nice weather, huh?", "ts": 1757195749.388263}, {"jp": "どうしたい？", "reading_kana": "どうしたい？", "en": "What do you want to do?", "ts": 1757195753.581344}, {"jp": "もう少し詳しく", "reading_kana": "もうすこし くわしく", "en": "More details", "ts": 1757195753.581344}, {"jp": "手伝おうか？", "reading_kana": "てつだおうか？", "en": "Shall I help?", "ts": 1757195753.581344}, {"jp": "次は何をしますか", "reading_kana": "つぎはなにをしますか", "en": "What will you do next?", "ts": 1757195758.741651}, {"jp": "もっと詳しく教えて", "reading_kana": "もっとくわしくおしえて", "en": "Tell me more details.", "ts": 1757195758.741651}, {"jp": "そのドローンについて", "reading_kana": "そのドローンについて", "en": "About that drone.", "ts": 1757195758.741651}]